s3_utility.py
mys3utility-0.0.1.dist-info/METADATA
mys3utility-0.0.1.dist-info/WHEEL
mys3utility-0.0.1.dist-info/top_level.txt
mys3utility-0.0.1.dist-info/RECORD
