Metadata-Version: 2.1
Name: mys3utility
Version: 0.0.1
Summary: s3 utility library
Home-page: UNKNOWN
Author: UNKNOWN
Author-email: UNKNOWN
License: UNKNOWN
Platform: UNKNOWN
Requires-Dist: boto3 (>=1.2)
